frameapi/__init__.py
frameapi/core.py
frameapi/request.py
frameapi/response.py
frameapi/templates/default.html
frame_API-0.1.6.dist-info/LICENSE
frame_API-0.1.6.dist-info/METADATA
frame_API-0.1.6.dist-info/WHEEL
frame_API-0.1.6.dist-info/top_level.txt
frame_API-0.1.6.dist-info/RECORD
